LICENSE
MANIFEST.in
README.md
requirements.txt
setup.py
cruddy/__init__.py
cruddy/_version
cruddy/calculatedvalue.py
cruddy/exceptions.py
cruddy/lambdaclient.py
cruddy/prototype.py
cruddy/response.py
cruddy.egg-info/PKG-INFO
cruddy.egg-info/SOURCES.txt
cruddy.egg-info/dependency_links.txt
cruddy.egg-info/entry_points.txt
cruddy.egg-info/requires.txt
cruddy.egg-info/top_level.txt
cruddy/scripts/__init__.py
cruddy/scripts/cli.py
samples/lambda_cruddy/README.md
samples/lambda_cruddy/item1.json
samples/lambda_cruddy/item2.json
samples/lambda_cruddy/kappa_template.yml
samples/lambda_cruddy/lambda_cruddy_cf_template.json
samples/lambda_cruddy/_src/README.md
samples/lambda_cruddy/_src/config.json
samples/lambda_cruddy/_src/dev_config.json
samples/lambda_cruddy/_src/lambda_cruddy.py