Metadata-Version: 1.1
Name: cruddy
Version: 0.12.0
Summary: A CRUD wrapper class for Amazon DynamoDB
Home-page: https://github.com/cloudnative/cruddy
Author: Mitch Garnaat
Author-email: mitch@cloudnative.io
License: Apache License 2.0
Platform: UNKNOWN
Classifier: Development Status :: 3 - Alpha
Classifier: Intended Audience :: Developers
Classifier: Intended Audience :: System Administrators
Classifier: Natural Language :: English
Classifier: License :: OSI Approved :: Apache Software License
Classifier: Programming Language :: Python
Classifier: Programming Language :: Python :: 2.7
Classifier: Programming Language :: Python :: 3
Classifier: Programming Language :: Python :: 3.3
Classifier: Programming Language :: Python :: 3.4
Classifier: Programming Language :: Python :: 3.5
